LICENSE
uberjob/__init__.py
uberjob/_builtins.py
uberjob/_errors.py
uberjob/_execution/__init__.py
uberjob/_execution/greedy.py
uberjob/_execution/run_function_on_graph.py
uberjob/_execution/run_physical.py
uberjob/_execution/scheduler.py
uberjob/_graph.py
uberjob/_plan.py
uberjob/_registry.py
uberjob/_rendering.py
uberjob/_run.py
uberjob/_testing/__init__.py
uberjob/_testing/test_mounted_file_store.py
uberjob/_testing/test_store.py
uberjob/_transformations/__init__.py
uberjob/_transformations/caching.py
uberjob/_transformations/pruning.py
uberjob/_util/__init__.py
uberjob/_util/networkx_util.py
uberjob/_util/retry.py
uberjob/_util/traceback.py
uberjob/_util/validation.py
uberjob/_value_store.py
uberjob/graph.py
uberjob/progress/__init__.py
uberjob/progress/_composite_progress_observer.py
uberjob/progress/_console_progress_observer.py
uberjob/progress/_html_progress_observer.py
uberjob/progress/_ipython_progress_observer.py
uberjob/progress/_null_progress_observer.py
uberjob/progress/_progress.py
uberjob/progress/_progress_observer.py
uberjob/progress/_simple_progress_observer.py
uberjob/stores/__init__.py
uberjob/stores/_binary_file_store.py
uberjob/stores/_file_store.py
uberjob/stores/_json_file_store.py
uberjob/stores/_literal_source.py
uberjob/stores/_modified_time_source.py
uberjob/stores/_mounted_store.py
uberjob/stores/_path_source.py
uberjob/stores/_pickle_file_store.py
uberjob/stores/_text_file_store.py
uberjob/stores/_touch_file_store.py
uberjob-1.0.0.dist-info/LICENSE
uberjob-1.0.0.dist-info/WHEEL
uberjob-1.0.0.dist-info/METADATA
uberjob-1.0.0.dist-info/RECORD
