Metadata-Version: 2.1
Name: uberjob
Version: 1.0.0
Summary: uberjob is a Python package for building and running call graphs.
Home-page: https://github.com/twosigma/uberjob
License: Apache-2.0
Author: Timothy Shields
Author-email: Timothy.Shields@twosigma.com
Requires-Python: >=3.7,<4.0
Classifier: License :: OSI Approved :: Apache Software License
Classifier: Programming Language :: Python :: 3
Classifier: Programming Language :: Python :: 3.10
Classifier: Programming Language :: Python :: 3.7
Classifier: Programming Language :: Python :: 3.8
Classifier: Programming Language :: Python :: 3.9
Requires-Dist: networkx (>=2.5,<3.0)
Requires-Dist: nxv (>=0.1.3,<0.2.0)
Project-URL: Documentation, https://uberjob.readthedocs.io/
Project-URL: Repository, https://github.com/twosigma/uberjob
